{
    "answers": {
        "manip_check_music_response": [],
        "manip_check_light_response": [],
        "manip_check_order": [],
        "manip_check_effect_order": [
            "play music",
            "turn on the light",
            "play music AND turn on the light"
        ],
        "action_response": "button",
        "goal_condition": "noGoal",
        "music_box": [
            "ButtonMusic.jpeg",
            "HandleMusic.jpeg",
            "BothMusicLight.jpeg"
        ],
        "hypotheses_slider_order_prior": "",
        "hypotheses_slider_order_posterior": "",
        "actions_buttons_order": "",
        "toy_inst_num": 0,
        "browser": "Chrome",
        "browser_height": 600,
        "browser_width": 1299,
        "screen_width": 1366,
        "screen_height": 768,
        "mobile_device": false,
        "prior_beliefs": [],
        "posterior_beliefs": [],
        "about": "choices",
        "why_action": "i like button pressing (gamer)",
        "age": "28",
        "gender": "m",
        "language": "english",
        "exp_start_time": "",
        "exp_end_time": "2018-01-18T23:23:51.324Z",
        "action_trial_start_time": "2018-01-18T23:22:44.109Z",
        "action_trial_end_time": "2018-01-18T23:23:02.575Z",
        "experiment_completion_time": "",
        "action_trial_time": "",
        "hyp_type": "posterior",
        "rand_slider_labels": [
            "HandleMusic",
            "BothMusicLight",
            "ButtonMusic"
        ],
        "rand_action_labels": [
            "Press the button and pull the handle<br>at the same time",
            "Pull the handle on its own",
            "Press the button on its own"
        ]
    },
    "AssignmentId": "3IKZ72A5B4GAOKHKXPSVEAR7QF5NFJ",
    "WorkerId": "AU0H6TLRW311L",
    "HITId": "36818Z1KV3D51598EOHM2BNM1XTA3U",
    "AssignmentStatus": "Submitted",
    "AutoApprovalTime": "2018-01-18T23:28:53Z",
    "AcceptTime": "2018-01-18T23:22:39Z",
    "SubmitTime": "2018-01-18T23:23:53Z",
    "Assignment": ""
}