{
    "answers": {
        "manip_check_music_response": [
            "button",
            "button",
            "both"
        ],
        "manip_check_light_response": [
            "handle",
            "handle",
            "both"
        ],
        "manip_check_order": [
            "HandleMusic",
            "ButtonMusic",
            "BothMusicLight"
        ],
        "manip_check_effect_order": [
            "play music",
            "turn on the light",
            "play music AND turn on the light"
        ],
        "outcome": "music",
        "action_response": "both",
        "goal_condition": "noGoal",
        "music_box": [
            "BothMusicLight.jpeg",
            "HandleMusic.jpeg",
            "ButtonMusic.jpeg"
        ],
        "hypotheses_slider_order_prior": [
            "HandleMusic",
            "BothMusicLight",
            "ButtonMusic"
        ],
        "hypotheses_slider_order_posterior": [
            "BothMusicLight",
            "HandleMusic",
            "ButtonMusic"
        ],
        "actions_buttons_order": "",
        "toy_inst_num": 3,
        "browser": "Chrome",
        "browser_height": 600,
        "browser_width": 1299,
        "screen_width": 1366,
        "screen_height": 768,
        "mobile_device": false,
        "prior_beliefs": [
            "27",
            "25",
            "26"
        ],
        "posterior_beliefs": [
            "39",
            "37",
            "36"
        ],
        "about": "Probability",
        "comment": "Nope",
        "age": "36",
        "gender": "m",
        "language": "English",
        "exp_start_time": "2018-01-16T05:44:45.326Z",
        "exp_end_time": "2018-01-16T05:50:21.087Z",
        "action_trial_start_time": "2018-01-16T05:47:43.491Z",
        "action_trial_end_time": "2018-01-16T05:48:20.424Z",
        "experiment_completion_time": 335761,
        "action_trial_time": 36933,
        "hyp_type": "posterior",
        "rand_slider_labels": [
            "HandleMusic",
            "BothMusicLight",
            "ButtonMusic"
        ],
        "rand_action_labels": [
            "Press the button and pull the handle<br>at the same time",
            "Press the button on its own",
            "Pull the handle on its own"
        ]
    },
    "AssignmentId": "3SNLUL3WO4N9J2BPG17FNIOLV4GLU4",
    "WorkerId": "A4T50ODN6SGNR",
    "HITId": "35XW21VSVGEQH5LR1U7DJXB9NPJSLE",
    "AssignmentStatus": "Submitted",
    "AutoApprovalTime": "2018-01-16T05:55:23Z",
    "AcceptTime": "2018-01-16T05:44:37Z",
    "SubmitTime": "2018-01-16T05:50:23Z",
    "Assignment": ""
}