{
 "AssignmentId": "32VNZTT0A74L52CN6FDTWQZRQS7R4B",
 "WorkerId": "a4fe998f1e7dba2f8317ba111d2ef671",
 "HITId": "3TUOHPJXYHXEOGJPZIK2RG9HFC9XWL",
 "AssignmentStatus": "Approved",
 "AutoApprovalTime": "2019-09-04T19:21:55.000Z",
 "AcceptTime": "2019-09-04T19:18:21.000Z",
 "SubmitTime": "2019-09-04T19:20:55.000Z",
 "ApprovalTime": "2019-09-04T19:21:56.000Z",
 "answers": {
  "trials": [
   {
    "trial_type": "activation",
    "toy": "cyl-lever.png",
    "toy_type": "left-lever",
    "action_number": 1,
    "action": "right-lever",
    "success": false,
    "rt": 4024
   },
   {
    "trial_type": "activation",
    "toy": "cyl-lever.png",
    "toy_type": "left-lever",
    "action_number": 2,
    "action": "left-lever",
    "success": true,
    "rt": 2353
   },
   {
    "trial_type": "activation",
    "toy": "cyl-lever.png",
    "toy_type": "left-lever",
    "action_number": 3,
    "action": "left-lever",
    "success": true,
    "rt": 2147
   },
   {
    "trial_type": "presentation",
    "toy": "cube-spinner.png",
    "toy_type": "left-spinner",
    "action_number": 1,
    "action": "right-spinner",
    "success": false,
    "rt": 3003
   },
   {
    "trial_type": "presentation",
    "toy": "cube-spinner.png",
    "toy_type": "left-spinner",
    "action_number": 2,
    "action": "left-spinner",
    "success": true,
    "rt": 2543
   },
   {
    "trial_type": "presentation",
    "toy": "cube-spinner.png",
    "toy_type": "left-spinner",
    "action_number": 3,
    "action": "left-spinner",
    "success": true,
    "rt": 1433
   },
   {
    "trial_type": "final_toy_choice",
    "toy": "cube-spinner.png",
    "toy_type": "NA",
    "action_number": "NA",
    "action": "NA",
    "success": "NA",
    "rt": 42120,
    "why_toy": "know how to use it and he doesn't know I know"
   }
  ],
  "system": {
   "Browser": "Chrome",
   "OS": "Windows",
   "screenH": 768,
   "screenW": 1366,
   "ip_data": {
    "ip": "2601:44:c180:f56:18f7:75df:8d45:b6d",
    "city": "Levittown",
    "region": "Pennsylvania",
    "region_code": "PA",
    "country": "US",
    "country_name": "United States",
    "continent_code": "NA",
    "in_eu": false,
    "postal": "19056",
    "latitude": 40.1519,
    "longitude": -74.8826,
    "timezone": "America/New_York",
    "utc_offset": "-0400",
    "country_calling_code": "+1",
    "currency": "USD",
    "languages": "en-US,es-US,haw,fr",
    "asn": "AS7922",
    "org": "Comcast Cable Communications, LLC"
   }
  },
  "goal_condition": "presentation",
  "social_condition": "social",
  "subject_information": {
   "language": "english",
   "enjoyment": "Better than average",
   "asses": "Yes",
   "age": "32",
   "gender": "Male",
   "education": "Some College",
   "comments": ""
  },
  "time_in_minutes": 2.3425833333333332
 }
}