{
 "AssignmentId": "3NL0RFNU0FNZIYZSGV4WVEDDV0G4KY",
 "WorkerId": "a551d823bdc41a8d1c140158249abef1",
 "HITId": "3TUOHPJXYHXEOGJPZIK2RG9HFC9XWL",
 "AssignmentStatus": "Approved",
 "AutoApprovalTime": "2019-09-04T19:51:58.000Z",
 "AcceptTime": "2019-09-04T19:29:53.000Z",
 "SubmitTime": "2019-09-04T19:50:58.000Z",
 "ApprovalTime": "2019-09-04T19:52:56.000Z",
 "answers": {
  "trials": [
   {
    "trial_type": "activation",
    "toy": "cyl-lever.png",
    "toy_type": "right-lever",
    "action_number": 1,
    "action": "left-lever",
    "success": false,
    "rt": 2925
   },
   {
    "trial_type": "activation",
    "toy": "cyl-lever.png",
    "toy_type": "right-lever",
    "action_number": 2,
    "action": "right-lever",
    "success": true,
    "rt": 3322
   },
   {
    "trial_type": "activation",
    "toy": "cyl-lever.png",
    "toy_type": "right-lever",
    "action_number": 3,
    "action": "right-lever",
    "success": true,
    "rt": 2069
   },
   {
    "trial_type": "presentation",
    "toy": "tri-button.png",
    "toy_type": "left-button",
    "action_number": 1,
    "action": "right-button",
    "success": false,
    "rt": 2163
   },
   {
    "trial_type": "presentation",
    "toy": "tri-button.png",
    "toy_type": "left-button",
    "action_number": 2,
    "action": "left-button",
    "success": true,
    "rt": 1844
   },
   {
    "trial_type": "presentation",
    "toy": "tri-button.png",
    "toy_type": "left-button",
    "action_number": 3,
    "action": "left-button",
    "success": true,
    "rt": 1542
   },
   {
    "trial_type": "final_toy_choice",
    "toy": "cyl-lever.png",
    "toy_type": "NA",
    "action_number": "NA",
    "action": "NA",
    "success": "NA",
    "rt": 17932,
    "why_toy": "I know the right lever will play music"
   }
  ],
  "system": {
   "Browser": "Chrome",
   "OS": "Mac",
   "screenH": 900,
   "screenW": 1440
  },
  "goal_condition": "presentation",
  "social_condition": "no_social",
  "subject_information": {
   "language": "English",
   "enjoyment": "Better than average",
   "asses": "Yes",
   "age": "34",
   "gender": "Female",
   "education": "Some College",
   "comments": "It was cute and fun! Thank you for letting me participate. "
  },
  "time_in_minutes": 2.23665
 }
}